Metadata-Version: 2.1
Name: byted-overpass-ic-tob-river-service
Version: 0.0.1
Summary: A simple package named byted_overpass_ic_tob_river_service
Home-page: https://github.com/artifact/byted_overpass_ic_tob_river_service.git
Author: artifact
Author-email: artifact@example.com
License: UNKNOWN
Platform: UNKNOWN
Classifier: Programming Language :: Python :: 3
Classifier: License :: OSI Approved :: MIT License
Classifier: Operating System :: OS Independent
